clc_analysis/Event.py
clc_analysis/__init__.py
clc_analysis/calculate_rms.py
clc_analysis/deblip_events.py
clc_analysis/detect.py
clc_analysis/extract_events.py
clc_analysis-0.0.1.dist-info/METADATA
clc_analysis-0.0.1.dist-info/WHEEL
clc_analysis-0.0.1.dist-info/top_level.txt
clc_analysis-0.0.1.dist-info/RECORD
